logHandler.py
my_log_handler-0.1.0.dist-info/LICENSE
my_log_handler-0.1.0.dist-info/METADATA
my_log_handler-0.1.0.dist-info/WHEEL
my_log_handler-0.1.0.dist-info/top_level.txt
my_log_handler-0.1.0.dist-info/RECORD
