Metadata-Version: 2.1
Name: my-log-handler
Version: 0.1.0
Summary: Add basic log functionality.
Home-page: https://github.com/bonnybabukachappilly/utils/tree/logHandler
Author: Bonny Babu
Author-email: bonnybabukachappilly@gmail.com
License: GNU GENERAL PUBLIC LICENSE Version 3
Platform: UNKNOWN
Classifier: Development Status :: 3 - Alpha
Classifier: License :: OSI Approved :: GNU General Public License v3 (GPLv3)
Classifier: Programming Language :: Python :: 3
Classifier: Programming Language :: Python :: 3.9
Classifier: Programming Language :: Python :: 3.10
License-File: LICENSE
Provides-Extra: dev
Requires-Dist: flake8 (>=4.0) ; extra == 'dev'
Requires-Dist: tox (>=3.25) ; extra == 'dev'
Requires-Dist: pytest (>=7.1) ; extra == 'dev'
Requires-Dist: pytest-cov (>=3.0) ; extra == 'dev'
Requires-Dist: mypy (>=0.961) ; extra == 'dev'
Requires-Dist: check-manifest (>=0.48) ; extra == 'dev'
Requires-Dist: twine (>=4.0) ; extra == 'dev'
